{
  "name": "@tank/tailwind",
  "version": "2.1.0",
  "description": "Tailwind CSS patterns and component recipes. Covers responsive design, dark mode, theme configuration, plugins, animations, and CSS variables. Includes shadcn/ui patterns. Triggers: tailwind, CSS, utility class, responsive, dark mode, theme, plugin, animation, shadow, gradient, flex, grid, container query, breakpoint, hover, focus, arbitrary value, shadcn, component styling, design tokens.",
  "permissions": {
    "network": {
      "outbound": []
    },
    "filesystem": {
      "read": [
        "**/*"
      ],
      "write": []
    },
    "subprocess": false
  },
  "repository": "https://github.com/tankpkg/skills"
}